enemera/__init__.py
enemera/client.py
enemera/api/__init__.py
enemera/api/base.py
enemera/api/italy/__init__.py
enemera/api/italy/ancillary_services.py
enemera/api/italy/dam_demand.py
enemera/api/italy/exchange_volumes.py
enemera/api/italy/flows.py
enemera/api/italy/generation.py
enemera/api/italy/imbalance.py
enemera/api/italy/load.py
enemera/api/italy/prices.py
enemera/api/italy/xbid.py
enemera/api/spain/__init__.py
enemera/api/spain/prices.py
enemera/api/spain/xbid.py
enemera/core/__init__.py
enemera/core/constants.py
enemera/core/exceptions.py
enemera/core/response.py
enemera/models/__init__.py
enemera/models/curves.py
enemera/models/enums.py
enemera/models/response_models.py
enemera/security/__init__.py
enemera/security/config.py
enemera/security/session.py
enemera/security/validators.py
enemera/utils/__init__.py
enemera/utils/logging.py
enemera/utils/utility_functions.py
enemera/validators/__init__.py
enemera/validators/validators.py
enemera-0.2.1.dist-info/licenses/LICENSE
enemera-0.2.1.dist-info/METADATA
enemera-0.2.1.dist-info/WHEEL
enemera-0.2.1.dist-info/top_level.txt
enemera-0.2.1.dist-info/RECORD
