Metadata-Version: 2.4
Name: enemera
Version: 0.2.1
Summary: API client for Enemera energy data API with enhanced functionality and enums
Home-page: https://github.com/fracasamax/enemera-api-client
Author: Francesco Casamassima
Author-email: Francesco Casamassima <dev@elnc.eu>
License: MIT
Project-URL: Homepage, https://github.com/fracasamax/enemera-api-client
Project-URL: Bug Tracker, https://github.com/fracasamax/enemera-api-client/issues
Project-URL: Documentation, https://github.com/fracasamax/enemera-api-client#readme
Classifier: Programming Language :: Python :: 3
Classifier: License :: OSI Approved :: MIT License
Classifier: Operating System :: OS Independent
Classifier: Development Status :: 4 - Beta
Classifier: Intended Audience :: Developers
Classifier: Topic :: Scientific/Engineering
Classifier: Topic :: Software Development :: Libraries
Requires-Python: >=3.7
License-File: LICENSE
Requires-Dist: requests>=2.25.0
Requires-Dist: pydantic>=2.0.0
Requires-Dist: python-dateutil>=2.8.0
Provides-Extra: pandas
Requires-Dist: pandas>=1.0.0; extra == "pandas"
Provides-Extra: polars
Requires-Dist: polars>=0.7.0; extra == "polars"
Provides-Extra: excel
Requires-Dist: pandas>=1.0.0; extra == "excel"
Requires-Dist: openpyxl>=3.0.0; extra == "excel"
Provides-Extra: excel-xlsxwriter
Requires-Dist: pandas>=1.0.0; extra == "excel-xlsxwriter"
Requires-Dist: xlsxwriter>=3.0.0; extra == "excel-xlsxwriter"
Provides-Extra: all
Requires-Dist: pandas>=1.0.0; extra == "all"
Requires-Dist: polars>=0.7.0; extra == "all"
Requires-Dist: openpyxl>=3.0.0; extra == "all"
Requires-Dist: xlsxwriter>=3.0.0; extra == "all"
Provides-Extra: dev
Requires-Dist: pytest>=7.0.0; extra == "dev"
Requires-Dist: black>=23.0.0; extra == "dev"
Requires-Dist: isort>=5.12.0; extra == "dev"
Requires-Dist: flake8>=6.0.0; extra == "dev"
Dynamic: author
Dynamic: home-page
Dynamic: license-file
Dynamic: requires-python
